cuboid_sphere/__init__.py
cuboid_sphere/client.py
cuboid_sphere/model_process.py
cuboid_sphere/process_depth_map.py
cuboid_sphere/process_image.py
cuboid_sphere/server.py
cuboid_sphere/test_Depth.py
cuboid_sphere-0.1.0.dist-info/METADATA
cuboid_sphere-0.1.0.dist-info/WHEEL
cuboid_sphere-0.1.0.dist-info/top_level.txt
cuboid_sphere-0.1.0.dist-info/RECORD
