Metadata-Version: 2.1
Name: cuboid-sphere
Version: 0.1.0
Summary: Finding Cuboid and Sphere in 3D Image and 2D image
Home-page: https://github.com/bendangnuksung/cuboid_sphere
Author: bendangnuksung
Author-email: bendangnuksungimsong@gmail.com
License: MIT License
Platform: UNKNOWN
Classifier: Programming Language :: Python :: 3
Classifier: Operating System :: OS Independent
Requires-Dist: h5py
Requires-Dist: numpy
Requires-Dist: opencv-python
Requires-Dist: matplotlib
Requires-Dist: requests
